src/__init__.py
src/const.py
src/encoder.py
src/gui.py
src/log.py
src/one_night.py
src/predictions.py
src/replay.py
src/solvers.py
src/statements.py
src/stats.py
src/util.py
wolfbot-0.0.1.dist-info/LICENSE
wolfbot-0.0.1.dist-info/METADATA
wolfbot-0.0.1.dist-info/WHEEL
wolfbot-0.0.1.dist-info/top_level.txt
wolfbot-0.0.1.dist-info/RECORD
