Metadata-Version: 2.1
Name: wolfbot
Version: 0.0.1
Summary: One Night Ultimate Werewolf: AI Edition
Home-page: https://github.com/tyleryep/wolfbot
Author: Tyler Yep
Author-email: tyep10@gmail.com
License: UNKNOWN
Platform: UNKNOWN
Classifier: Programming Language :: Python :: 3
Classifier: License :: OSI Approved :: MIT License
Classifier: Operating System :: OS Independent
Requires-Python: >=3.9
